dep2req-1.0.5.dist-info/METADATA
dep2req-1.0.5.dist-info/WHEEL
dep2req-1.0.5.dist-info/entry_points.txt
dep2req-1.0.5.dist-info/licenses/LICENSE
dep2req/__init__.py
dep2req/deptoreq.py
dep2req-1.0.5.dist-info/RECORD
