Metadata-Version: 2.1
Name: dep2req
Version: 1.0.5
Summary: Create a requirements.txt from dependencies in a pyproject.toml
Author-Email: Greg Smethells <gsmethells@gmail.com>
License: GPL-2.0+
Classifier: Programming Language :: Python :: 3
Classifier: License :: OSI Approved :: GNU General Public License v2 (GPLv2)
Classifier: Operating System :: OS Independent
Project-URL: Homepage, https://gitlab.com/oldmission/dep2req
Project-URL: Bug tracker, https://gitlab.com/oldmission/dep2req/-/issues
Requires-Python: >=3.7
Requires-Dist: toml
